{
  "timestamp": "2026-04-01T05:00:21Z",
  "total_value_usd": 253218.20,
  "chains": {
    "solana": {
      "total_usd": 0,
      "holdings": []
    },
    "ethereum": {
      "total_usd": 0,
      "holdings": []
    },
    "base": {
      "total_usd": 0,
      "holdings": []
    },
    "hyperevm": {
      "total_usd": 0,
      "holdings": []
    },
    "hyperliquid_spot": {
      "total_usd": 137961.96963514577,
      "holdings": [
        {
          "chain": "hyperliquid-spot",
          "token": "USDC",
          "balance": "80049.33556719",
          "price_usd": 1,
          "value_usd": 80049.33556719
        },
        {
          "chain": "hyperliquid-spot",
          "token": "UBTC",
          "balance": "0.7756458115",
          "price_usd": 68232.5,
          "value_usd": 52924.25283317375
        },
        {
          "chain": "hyperliquid-spot",
          "token": "HYPE",
          "balance": "136.51463383",
          "price_usd": 36.541,
          "value_usd": 4988.381234782029
        }
      ]
    },
    "hyperliquid_perps": {
      "account_value": 115256.227313,
      "details": {
        "account_value": 115256.227313,
        "total_margin_used": 0.0,
        "positions": []
      }
    }
  },
  "open_orders": [
    {
      "coin": "@142",
      "side": "buy",
      "price": 52000.0,
      "size": 0.96153,
      "value_usd": 49999.56
    },
    {
      "coin": "@142",
      "side": "buy",
      "price": 60000.0,
      "size": 0.33333,
      "value_usd": 19999.8
    }
  ]
}
